.gitignore
LICENSE
MANIFEST.in
Makefile
README.rst
requirements.txt
setup.py
address_parser/__init__.py
address_parser/parser.py
address_parser.egg-info/PKG-INFO
address_parser.egg-info/SOURCES.txt
address_parser.egg-info/dependency_links.txt
address_parser.egg-info/top_level.txt
address_parser/support/suffixes.csv
docs/Makefile
docs/conf.py
docs/index.rst
tests/__init__.py
tests/test_basic.py
tests/support/bad_business_addresses.txt
tests/support/bad_license_addresses.txt
tests/support/crime_addresses.txt
tests/support/good_segments.txt
tests/support/missing_street_type.txt
tests/support/test_geocoder_addresses.txt