Metadata-Version: 1.1
Name: address-parser
Version: 1.0.0
Summary: Address parser
Home-page: https://github.com/CivicKnowledge/address_parser
Author: Eric Busboom
Author-email: eric@sandiegodata.org
License: MIT
Platform: UNKNOWN
Classifier: Development Status :: 4 - Beta
Classifier: Environment :: Web Environment
Classifier: Framework :: Django
Classifier: Intended Audience :: Developers
Classifier: License :: OSI Approved :: MIT License
Classifier: Operating System :: OS Independent
Classifier: Programming Language :: Python
Classifier: Programming Language :: Python :: 3.4
Classifier: Topic :: Software Development :: Debuggers
Classifier: Topic :: Software Development :: Libraries :: Python Modules
